bunka_superfunctions/.DS_Store
bunka_superfunctions/_init_.py
bunka_superfunctions/clean_tweets.py
bunka_superfunctions/networks.py
bunka_superfunctions/specificity.py
bunka_superfunctions/toxic.py
bunka_superfunctions-0.7.0.dist-info/WHEEL
bunka_superfunctions-0.7.0.dist-info/METADATA
bunka_superfunctions-0.7.0.dist-info/RECORD
